addana/__init__.py
addana/__main__.py
addana/drawer.py
addana/exceptions.py
addana/pca.csv
addana/structures.py
addana-0.0.28.dist-info/LICENSE
addana-0.0.28.dist-info/METADATA
addana-0.0.28.dist-info/WHEEL
addana-0.0.28.dist-info/dependency_links.txt
addana-0.0.28.dist-info/top_level.txt
addana-0.0.28.dist-info/RECORD
