Metadata-Version: 2.1
Name: addana
Version: 0.0.28
Summary: address
Home-page: https://github.com/advancehs/addana
Author: advancehs
Author-email: 1019753743@11.com
License: MIT license
Keywords: addana
Classifier: Development Status :: 2 - Pre-Alpha
Classifier: Intended Audience :: Developers
Classifier: License :: OSI Approved :: MIT License
Classifier: Natural Language :: English
Classifier: Programming Language :: Python :: 3
Classifier: Programming Language :: Python :: 3.7
Classifier: Programming Language :: Python :: 3.8
Classifier: Programming Language :: Python :: 3.9
Classifier: Programming Language :: Python :: 3.10
Requires-Python: >=3.7
License-File: LICENSE
Requires-Dist: pyecharts
Requires-Dist: pandas
Requires-Dist: jieba
Requires-Dist: folium
